kmeans_pytorch/__init__.py
kmeans_pytorch/main.py
kmeans_pytorch-0.3.dist-info/LICENSE
kmeans_pytorch-0.3.dist-info/METADATA
kmeans_pytorch-0.3.dist-info/WHEEL
kmeans_pytorch-0.3.dist-info/entry_points.txt
kmeans_pytorch-0.3.dist-info/top_level.txt
kmeans_pytorch-0.3.dist-info/RECORD
