Metadata-Version: 2.1
Name: kmeans_pytorch
Version: 0.3
Summary: UNKNOWN
Home-page: https://github.com/subhadarship/kmeans_pytorch
Author: Subhadarshi
Author-email: subhadarshipanda08@gmail.com
License: License :: OSI Approved :: MIT License
Platform: UNKNOWN
Classifier: Programming Language :: Python
Requires-Python: >=3.6
